Metadata-Version: 2.1
Name: odoo-addon-shopfloor_mobile_base_auth_api_key
Version: 18.0.1.0.0.3
Requires-Python: >=3.10
Requires-Dist: odoo-addon-auth_api_key_group==18.0.*
Requires-Dist: odoo-addon-shopfloor_mobile_base==18.0.*
Requires-Dist: odoo==18.0.*
Summary: Provides authentication via API key to Shopfloor base mobile app
Home-page: https://github.com/OCA/shopfloor-app
License: LGPL-3
Author: Camptocamp, Odoo Community Association (OCA)
Author-email: support@odoo-community.org
Classifier: Programming Language :: Python
Classifier: Framework :: Odoo
Classifier: Framework :: Odoo :: 18.0
Classifier: License :: OSI Approved :: GNU Lesser General Public License v3 (LGPLv3)
Classifier: Development Status :: 4 - Beta
